Metadata-Version: 1.0
Name: psy-distributions
Version: 0.2
Summary: Gaussian and Binomial distributions
Home-page: UNKNOWN
Author: Nazım Önder Orhan
Author-email: UNKNOWN
License: UNKNOWN
Platform: UNKNOWN
